datalib_ym/__init__.py
datalib_ym/advanced_analysis.py
datalib_ym/data_manipulation.py
datalib_ym/statistics.py
datalib_ym/visualization.py
datalib_ym-1.0.1.dist-info/LICENSE
datalib_ym-1.0.1.dist-info/METADATA
datalib_ym-1.0.1.dist-info/WHEEL
datalib_ym-1.0.1.dist-info/top_level.txt
datalib_ym-1.0.1.dist-info/RECORD
