Metadata-Version: 2.1
Name: datalib_ym
Version: 1.0.1
Summary: A comprehensive library for data manipulation, analysis, and visualization
Home-page: https://github.com/miledyessine/datalib_ym
Author: Yessine Miled
Author-email: miled.yassine7@gmail.com
License: MIT
Classifier: Development Status :: 3 - Alpha
Classifier: Intended Audience :: Developers
Classifier: License :: OSI Approved :: MIT License
Classifier: Operating System :: OS Independent
Classifier: Programming Language :: Python :: 3
Classifier: Programming Language :: Python :: 3.7
Classifier: Programming Language :: Python :: 3.8
Classifier: Programming Language :: Python :: 3.9
Requires-Python: >=3.7
License-File: LICENSE
Requires-Dist: numpy (>=1.19.0)
Requires-Dist: pandas (>=1.1.0)
Requires-Dist: matplotlib (>=3.3.0)
Requires-Dist: seaborn (>=0.11.0)
Requires-Dist: scikit-learn (>=0.23.0)
Requires-Dist: scipy (>=1.5.0)
